{"id":39,"sort":80,"_id":"0gI0vofCzDqWb4G7"}
{"id":21,"sort":54,"_id":"0oSzfY80disKKDMq"}
{"id":13,"sort":35,"_id":"11Z6mzdd9Y9CIqwG"}
{"id":215,"sort":47,"_id":"26Ggwrl0ipeOq8PU"}
{"id":151,"sort":65,"_id":"2hElfoWvuTwGJgv5"}
{"id":73,"sort":89,"_id":"4anksBH3fvvsysYd"}
{"id":4,"sort":3,"_id":"699mSCrEWtjkqmL5"}
{"id":154,"sort":64,"_id":"6A3gihKh338ziwod"}
{"id":76,"sort":14,"_id":"7HgXiu5Q41Om1ff1"}
{"id":119,"sort":4,"_id":"7KrXoUdfi2wTeMkY"}
{"id":125,"sort":37,"_id":"8A8AYpFr0LWV7xlY"}
{"id":90,"sort":10,"_id":"8rrVhPHtJywjhJDk"}
{"id":30,"sort":70,"_id":"8svMBv4oMCGLg4VN"}
{"id":60,"sort":63,"_id":"91d3SrRcyQj3653q"}
{"id":133,"sort":19,"_id":"9vzvUnboy7mQwzxz"}
{"id":152,"sort":58,"_id":"BEjE9nJJOuctWMGA"}
{"id":162,"sort":9,"_id":"DaM0kl1zeqcNLOrw"}
{"id":14,"sort":36,"_id":"E26jotQFITF2sl6e"}
{"id":8,"sort":20,"_id":"FEFUgkrJCwKEFLJW"}
{"id":166,"sort":92,"_id":"FcH8yKv7uS88qiU5"}
{"id":5,"sort":7,"_id":"FgPHcLjIfPuWloHc"}
{"id":183,"sort":25,"_id":"HAjyJkfXUZqLJSuF"}
{"id":139,"sort":6,"_id":"HwmRpfjT4VcBb0QO"}
{"id":182,"sort":55,"_id":"IxxHJcD8y7VtaADm"}
{"id":34,"sort":85,"_id":"KIOsbwyX9tnhJKco"}
{"id":50,"sort":11,"_id":"KeJDp2KPnsxu5CLN"}
{"id":161,"sort":24,"_id":"KsC7PqGPSvIdHRy3"}
{"id":156,"sort":61,"_id":"KwUeCE490WMt6xED"}
{"id":40,"sort":81,"_id":"Lf7dgju73IqPCqkb"}
{"id":72,"sort":87,"_id":"Ll2lo83cYsLA7qom"}
{"id":109,"sort":59,"_id":"Nm2ynZXQST1YSLfF"}
{"id":149,"sort":76,"_id":"O6UIvye1Q4XKchXf"}
{"id":10,"sort":31,"_id":"OTBaAR2T9VP2Kz2K"}
{"id":15,"sort":38,"_id":"PONJm5SDNos0O4bc"}
{"id":192,"sort":18,"_id":"PjKYUOC3NazOMQYT"}
{"id":11,"sort":28,"_id":"QQ0TNf6uV2tDiLKy"}
{"id":7,"sort":12,"_id":"RzQfAr9yUIlxdJNk"}
{"id":135,"sort":32,"_id":"S0eTaQHnVyw5OlEC"}
{"id":65,"sort":5,"_id":"SSNgG1c3xrp8k36t"}
{"id":117,"sort":23,"_id":"ShTmIciNB9ZG1rB6"}
{"id":106,"sort":67,"_id":"SmpbRk0tdYqB8FLV"}
{"id":122,"sort":2,"_id":"St4fTWg1WOyi7LGW"}
{"id":131,"sort":82,"_id":"T3fYQFtqjOn5GKMX"}
{"id":96,"sort":57,"_id":"UnA7iZ8eMntluhmq"}
{"id":204,"sort":90,"_id":"W5a4z52cWkS3xThP"}
{"id":103,"sort":17,"_id":"WCO5emfjPItWN6GU"}
{"id":164,"sort":45,"_id":"WHFgzsxBZnvpdUya"}
{"id":45,"sort":78,"_id":"XWlisn9Ugd3hQb6t"}
{"id":6,"sort":8,"_id":"YN7D4vVioLvpCetY"}
{"id":36,"sort":33,"_id":"YPf268hr6IHCTCDN"}
{"id":59,"sort":43,"_id":"a6OkRGHBRsAzwv7S"}
{"id":198,"sort":53,"_id":"bGt8jALpKHJQHLUa"}
{"id":157,"sort":62,"_id":"bSL7Yfn4GcGNNBNM"}
{"id":27,"sort":66,"_id":"bTzOaNSNcpjNOLjz"}
{"id":25,"sort":42,"_id":"bUqBK1CMrUXD3Zk6"}
{"id":89,"sort":71,"_id":"biWvAtFdDSp1AFbZ"}
{"id":74,"sort":95,"_id":"bjNkVriDtO5ZFa5y"}
{"id":190,"sort":16,"_id":"cSWZesZyrDekvGNU"}
{"id":114,"sort":15,"_id":"cZ6n7dLmfFY1VYi2"}
{"id":104,"sort":13,"_id":"cv8ieCDbb2dWoKN5"}
{"id":205,"sort":56,"_id":"d9Hb3ub3oeAkr3Cz"}
{"id":58,"sort":39,"_id":"dgz9DA1Ka5BUCasf"}
{"id":210,"sort":97,"_id":"e2P0IBlPO15GeU00"}
{"id":20,"sort":52,"_id":"eKR4HKHgT58JGLZC"}
{"id":137,"sort":21,"_id":"eTlqYwWKEMbmtXCP"}
{"id":134,"sort":29,"_id":"edc0DQ7FbbgwHwZ0"}
{"id":120,"sort":83,"_id":"elPh8Lwjve6EHu1L"}
{"id":128,"sort":27,"_id":"fTE0LoAGSDHyovMa"}
{"id":68,"sort":91,"_id":"fVjtSnWS8VZOpQxK"}
{"id":203,"sort":88,"_id":"gIxT6lRytDZCArxb"}
{"id":163,"sort":41,"_id":"gVU2yT3xLIoex0Yo"}
{"id":102,"sort":44,"_id":"gaF0pIkXLRvZY1XK"}
{"id":121,"sort":84,"_id":"hUMM0Jb6xPfBqNMe"}
{"id":179,"sort":40,"_id":"irIK5MIpgi4KvuIT"}
{"id":46,"sort":74,"_id":"iswS2IitrenySBze"}
{"id":44,"sort":77,"_id":"k8Tgg6uBxBAPJHsq"}
{"id":116,"sort":34,"_id":"kjsAdOod5tQ51cAg"}
{"id":19,"sort":49,"_id":"kvT8tQ1KIknnA218"}
{"id":28,"sort":68,"_id":"lqDJgsX0JbmukaBp"}
{"id":49,"sort":79,"_id":"oFVLvcKjCMXAnm6m"}
{"id":47,"sort":75,"_id":"oO3mbyn9r5k2wI4K"}
{"id":9,"sort":26,"_id":"ok4c6M8Ai3K7f9YF"}
{"id":141,"sort":73,"_id":"po6IlCqdf0QyQJhA"}
{"id":63,"sort":1,"_id":"ps9B57mFCq8kxh0E"}
{"id":88,"sort":69,"_id":"qBhCqMZEuYiczXq0"}
{"id":2,"sort":0,"_id":"qq3FlSY1EHg7iMFb"}
{"id":216,"sort":48,"_id":"rCy9b3zCdjr1NFDo"}
{"id":193,"sort":93,"_id":"rsrhohIOLOJNWp25"}
{"id":165,"sort":46,"_id":"vqOwshhtgceHGRrl"}
{"id":66,"sort":30,"_id":"wdYJmCMk3NFvjOTB"}
{"id":153,"sort":60,"_id":"xJ5Lvi8RZaJBGfVt"}
{"id":181,"sort":51,"_id":"xoCLhwnIx4axHE10"}
{"id":105,"sort":22,"_id":"y0mctVDknB5q0TrB"}
{"id":31,"sort":72,"_id":"yArx1iZAbFSgu4Li"}
{"id":87,"sort":86,"_id":"z0DL75vzNbKhAaWc"}
{"id":197,"sort":50,"_id":"z0zY2x5znPpx7xbE"}
{"id":140,"sort":96,"_id":"zDAYrbKMvfV9iSlR"}
{"id":167,"sort":94,"_id":"zJ2uvMEPThsHpJqh"}
