{"id":4,"sort":3,"_id":"0NelYzKkGOfdoSDV"}
{"id":31,"sort":54,"_id":"0UVgHDCX8cD9RVNE"}
{"id":140,"sort":70,"_id":"1Ao82MxnOGY213dH"}
{"id":39,"sort":62,"_id":"1wIy6HIVVM0x1cYw"}
{"id":121,"sort":65,"_id":"1xJ3nkzymsVpDXNn"}
{"id":120,"sort":64,"_id":"2L0MbmsF73adeL2Z"}
{"id":44,"sort":56,"_id":"36v84HbR1TfW5FPy"}
{"id":21,"sort":43,"_id":"3ZUGMuuryS89z720"}
{"id":117,"sort":20,"_id":"8B0mNVpmMB6qyrwA"}
{"id":96,"sort":45,"_id":"8XFrlmOXZ1rq9iBn"}
{"id":46,"sort":58,"_id":"8XmBFju6PfLb7ljb"}
{"id":128,"sort":24,"_id":"8rlINjhFHg5XciDd"}
{"id":68,"sort":66,"_id":"BaRTA0cIWTTudRBc"}
{"id":28,"sort":50,"_id":"BfkAwIvZnG3aIVSQ"}
{"id":133,"sort":16,"_id":"DemC1wcaOgaGI61v"}
{"id":179,"sort":35,"_id":"DthVgIdU7HqNbzqr"}
{"id":105,"sort":19,"_id":"EeVqFzglGkvvZc3h"}
{"id":114,"sort":14,"_id":"EiDuZePAmnGuJ5rz"}
{"id":139,"sort":6,"_id":"FJGEXNKxnsXdr7Jc"}
{"id":152,"sort":47,"_id":"FTTC7vN2IBOxRFcV"}
{"id":141,"sort":55,"_id":"FXd09UoZ70sQ8rXB"}
{"id":45,"sort":57,"_id":"Fgxv4MEMd5D0eINP"}
{"id":5,"sort":7,"_id":"FvkA4AWBvTK89sNg"}
{"id":109,"sort":46,"_id":"IpQqCVqDCtGANNMr"}
{"id":25,"sort":37,"_id":"JVwPJKHqDmV8ARrB"}
{"id":135,"sort":27,"_id":"KJO7X9e3Rj8tsuMd"}
{"id":183,"sort":22,"_id":"M7cecfCM9zLOaymn"}
{"id":76,"sort":13,"_id":"My01CXmwO8O9RBmO"}
{"id":119,"sort":4,"_id":"MyTIgKns6WDhLvR5"}
{"id":15,"sort":33,"_id":"Oh5VI8v6LoqFUHlS"}
{"id":9,"sort":23,"_id":"QFOmUXsoQ6Gq2mfl"}
{"id":14,"sort":31,"_id":"Su5OJNcu1xS9yGfL"}
{"id":137,"sort":18,"_id":"SuCrJuzHkXBc2R2m"}
{"id":65,"sort":5,"_id":"TZbpQq1BLlzgoNtK"}
{"id":116,"sort":29,"_id":"TtTIityjWZdTU8bt"}
{"id":7,"sort":11,"_id":"UsbcICRGNmgxq3v9"}
{"id":20,"sort":42,"_id":"Vzk7J88vzFFOu4lr"}
{"id":90,"sort":9,"_id":"WUGh00RRhATBdOUB"}
{"id":50,"sort":10,"_id":"XLemVCzWNeVkhem1"}
{"id":134,"sort":26,"_id":"XPAd8jglcAhvzVQ5"}
{"id":8,"sort":17,"_id":"XZHncX8pvMhtEi7S"}
{"id":6,"sort":8,"_id":"YHdWw4c7juQ7hMl8"}
{"id":63,"sort":1,"_id":"ZFDNysPT7RNX5WgY"}
{"id":30,"sort":52,"_id":"bI1Q5IdGV5ccn99y"}
{"id":13,"sort":30,"_id":"c5imRDs1bsBe3Tsn"}
{"id":166,"sort":67,"_id":"cAzUTBvTwCSJrc8W"}
{"id":40,"sort":63,"_id":"cBPgtnTKHaW8Wytg"}
{"id":149,"sort":60,"_id":"d3x5JPqfPUECGqle"}
{"id":163,"sort":36,"_id":"fCSQzTpuEwICgBEc"}
{"id":181,"sort":41,"_id":"gRXtZBSfMOJ2yvMl"}
{"id":47,"sort":59,"_id":"gUO1HwGDjXTqMFVK"}
{"id":125,"sort":32,"_id":"joMxrYgl7xqoysMa"}
{"id":89,"sort":53,"_id":"kLQOP3Lo1tY29TB5"}
{"id":102,"sort":39,"_id":"kZJFlqWIpEwsvVo5"}
{"id":19,"sort":40,"_id":"knc8LwTc6tgmiVuc"}
{"id":167,"sort":68,"_id":"knxzNmsdXV0YjbyP"}
{"id":2,"sort":0,"_id":"m3N4z7by9QzvT3cl"}
{"id":11,"sort":25,"_id":"mRHfJUdjk9TxlsQA"}
{"id":88,"sort":51,"_id":"mX6oM6ko6R27Cd4E"}
{"id":74,"sort":69,"_id":"n7lIauexZlEeNUz7"}
{"id":58,"sort":34,"_id":"pNumh6Q46AmDdndU"}
{"id":106,"sort":49,"_id":"qKaErvAIndh92m3E"}
{"id":27,"sort":48,"_id":"qkQCPLOwkSVT2S3W"}
{"id":104,"sort":12,"_id":"rJmk1YbACHWUzsdm"}
{"id":36,"sort":28,"_id":"shkChd9FFjwb9z9X"}
{"id":103,"sort":15,"_id":"snNHMenUFiEqHCpP"}
{"id":49,"sort":61,"_id":"tuQU9HWQpALQ1fpI"}
{"id":182,"sort":44,"_id":"vIhCrrLqOi1rbxv5"}
{"id":161,"sort":21,"_id":"wlcMQZOuiyohv467"}
{"id":122,"sort":2,"_id":"y49tLAXDDoNa6sQG"}
{"id":59,"sort":38,"_id":"zzzHTSDMDa4Ji5Tz"}
