{
	"packages": {
		"app": {
			"version":	"0.5.5.0",
			"path":		"data/2015-06-12/app.nwjs-data",
			"bytes":	15741978
		},
		"app-db": {
			"version":	"1.2.5.0",
			"path":		"data/2015-06-12-2/app-db.nwjs-data",
			"bytes":	98994
		},
		"pics": {
			"version":	"1.2.4.0",
			"path":		"data/2015-06-12/pics.nwjs-data",
			"bytes":	37673590
		}
	},
	"homepage": "http://fleet.diablohu.com/",
	"release-notes": "https://github.com/Diablohu/WhoCallsTheFleet/releases",
	"forum": "http://bbs.ngacn.cc/read.php?tid=7959995"
}
